rajant_api/Alert_pb2.py
rajant_api/Backup_pb2.py
rajant_api/Common_pb2.py
rajant_api/ConfigMeta_pb2.py
rajant_api/Config_pb2.py
rajant_api/Event_pb2.py
rajant_api/FileTransfer_pb2.py
rajant_api/Gps_pb2.py
rajant_api/Hardware_pb2.py
rajant_api/Image_pb2.py
rajant_api/Led_pb2.py
rajant_api/Log_pb2.py
rajant_api/Message_pb2.py
rajant_api/ModelDatabase_pb2.py
rajant_api/Rule_pb2.py
rajant_api/Sam_pb2.py
rajant_api/Snapshot_pb2.py
rajant_api/StateMeta_pb2.py
rajant_api/State_pb2.py
rajant_api/Sup_pb2.py
rajant_api/System_pb2.py
rajant_api/Troip_pb2.py
rajant_api/__init__.py
rajant_api/rajant.py
rajant_api-0.1.1.dist-info/LICENSE
rajant_api-0.1.1.dist-info/METADATA
rajant_api-0.1.1.dist-info/WHEEL
rajant_api-0.1.1.dist-info/top_level.txt
rajant_api-0.1.1.dist-info/RECORD
