Metadata-Version: 2.1
Name: rajant-api
Version: 0.1.1
Summary: Library for communicating with Rajant Breadcrumb devices using the BCAPI implemented in Python3
Home-page: https://github.com/MrTwister96/rajant-api
Author: Schalk Olivier
Author-email: olivierschalk1@gmail.com
License: License :: Free For Educational Use
Classifier: Development Status :: 3 - Alpha
Classifier: Intended Audience :: Developers
Classifier: License :: Free For Educational Use
Classifier: Programming Language :: Python :: 3
Classifier: Programming Language :: Python :: 3.6
Classifier: Programming Language :: Python :: 3.7
Classifier: Programming Language :: Python :: 3.8
License-File: LICENSE
Requires-Dist: grpcio (==1.56.2)
Requires-Dist: grpcio-tools (==1.56.2)
Requires-Dist: protobuf (==4.23.4)
